remotedict/__init__.py
remotedict/constants.py
remotedict/azure/__init__.py
remotedict/azure/azure_dictionary.py
remotedict/azure/azure_queue.py
remotedict/azure/index/__init__.py
remotedict/azure/index/azure_index.py
remotedict/exceptions/__init__.py
remotedict/exceptions/item_locked_exception.py
remotedict/utils/__init__.py
remotedict/utils/serialization.py
remotedict-0.0.2.dist-info/METADATA
remotedict-0.0.2.dist-info/WHEEL
remotedict-0.0.2.dist-info/top_level.txt
remotedict-0.0.2.dist-info/RECORD
