Metadata-Version: 2.1
Name: remotedict
Version: 0.0.2
Summary: Remote dictionary backed up by cloud services
Home-page: http://github.com/ipazc/remotedict
Author: Iván de Paz Centeno
Author-email: ipazc@unileon.es
License: UNKNOWN
Keywords: Dictionary remote hosted cloud Azure blobs
Platform: UNKNOWN
Classifier: Environment :: Console
Classifier: Intended Audience :: Developers
Classifier: Intended Audience :: Education
Classifier: Intended Audience :: Science/Research
Classifier: Natural Language :: English
Classifier: Programming Language :: Python :: 3.4
Classifier: Programming Language :: Python :: 3.5
Classifier: Programming Language :: Python :: 3.6
Classifier: Programming Language :: Python :: 3.7
Requires-Dist: joblib (>=0.15.1)
Requires-Dist: lz4 (>=3.1.3)
Requires-Dist: azure-storage-blob (>=12.8.0)
Requires-Dist: azure-storage-queue (>=12.3.0)
